README.md
setup.py
image_match/__init__.py
image_match/elasticsearch_driver.py
image_match/goldberg.py
image_match/mongodb_driver.py
image_match/signature_database_base.py
tests/__init__.py
tests/test_elasticsearch_driver.py
tests/test_elasticsearch_driver_metadata_as_nested.py
tests/test_goldberg.py
vmn_image_match.egg-info/PKG-INFO
vmn_image_match.egg-info/SOURCES.txt
vmn_image_match.egg-info/dependency_links.txt
vmn_image_match.egg-info/requires.txt
vmn_image_match.egg-info/top_level.txt
vmn_image_match.egg-info/zip-safe