Metadata-Version: 2.1
Name: vmn-image-match
Version: 0.0.2
Summary: image_match is a simple package for finding approximate image matches from a corpus.
Home-page: https://github.com/tfemson/image-match/
Author: Femson Adeyeye
Author-email: tfemson@gmail.com
License: Apache License 2.0
Platform: UNKNOWN
Classifier: Development Status :: 4 - Beta
Classifier: Intended Audience :: Developers
Classifier: Topic :: Database
Classifier: Topic :: Database :: Database Engines/Servers
Classifier: Topic :: Software Development
Classifier: Natural Language :: English
Classifier: License :: OSI Approved :: Apache Software License
Classifier: Programming Language :: Python :: 3
Classifier: Programming Language :: Python :: 3.4
Classifier: Operating System :: MacOS :: MacOS X
Classifier: Operating System :: POSIX :: Linux
Classifier: Topic :: Multimedia :: Graphics
Provides-Extra: docs
Provides-Extra: dev
Provides-Extra: extra
Provides-Extra: test
